{
  "ITEM_NUM": "103",
  "QTY": 1,
  "JOW": 1,
  "JOH": 1,
  "JD": 1,
  "FIRE_RATING": 1,
  "DOOR_QTY": 1,
  "SUBMITTAL": false,
  "APPROVAL": false,
  "DOOR_LABEL_CONSTRUCTION": false,
  "MULTIPLE_TAGS": false,
  "SDI_LOCATION": false,
  "OPENING_TYPE": 1,
  "HANDI_": 0,
  "productType": "SDI",
  "standards": {
    "HINGE_GAP": 0.125,
    "STRIKE_GAP": 0.125,
    "TOP_GAP": 0.125,
    "UNDERCUT": 0.75,
    "DOOR_GAP": 0.09375,
    "CLOSURE_CHANNEL_CLEARANCE": 2.125,
    "CORE_CLEARANCE": 1,
    "CORE_EDGE_SPACE": 6,
    "DRYWALL_ALLOWANCE": 0.75,
    "DOOR_THICKNESS": 1.75,
    "TOP_CHANNEL_DEPTH": 0.75,
    "BOTTOM_CHANNEL_DEPTH": 0.75,
    "TOP_CHANNEL_THICKNESS": 0.05,
    "BOTTOM_CHANNEL_THICKNESS": 0.05,
    "DOOR_WIDTH_ADJUSTMENT": 0,
    "DOOR_CONSTRUCTION": "LOCKSEAM",
    "TOP_EDGE": "INVERTED",
    "BOTTOM_EDGE": "INVERTED",
    "DOOR_EDGE_REINFORCEMENT": false,
    "STOPP": 0.625,
    "RABBET": 1.9375,
    "XRABBET": 1.9375,
    "RETURN": 0.5,
    "XRETURN": 0.5,
    "DW_RTRN": "NONE",
    "XDW_RTRN": "NONE",
    "MINIMUM_SOFFIT": 1.25,
    "HEAD_STOPP": 0.625,
    "SILL_STOPP": 0.625,
    "FACEE": 2,
    "XFACEE": 2,
    "HEAD": 2,
    "XHEAD": 2,
    "SILL": 2,
    "XSILL": 2,
    "TRANSOM_HEAD": 2,
    "FRAME_CONSTRUCTION": "FACE WELDED",
    "SECTION": 2,
    "MAXIMUM_HINGE_SPACING": 36,
    "MAXIMUM_HINGE_SPACING_2": 11,
    "TOP_HINGE": 7.25,
    "BOTTOM_HINGE": 12.25,
    "HINGE_EDGE_SHAPE": "BEVEL",
    "JAMB_HINGE_SETBACK": 0.375,
    "DOOR_HINGE_SETBACK": 0.28125,
    "DOOR_FACE_SETBACK": 0.09375,
    "BUTT_HINGE_HEIGHT_ALLOWANCE": 0.005,
    "BUTT_HINGE_WIDTH_ALLOWANCE": 0,
    "BUTT_HINGE_THICKNESS_ALLOWANCE": 0.015,
    "CONTINUOUS_HINGE_REINFORCEMENT": true,
    "HINGES": true,
    "HINGE_DIMENSION_METHOD": 0,
    "STRIKE_EDGE_SHAPE": "BEVEL",
    "PRIMARY_STRIKE_CENTER": 40.3125,
    "ANCHOR_TYPE": 3,
    "ANCHOR_JB_DIST": 7.25,
    "ANCHOR_JT_DIST": 7.25,
    "ANCHOR_JMAX": 24,
    "ANCHOR_HDJ_DIST": 6,
    "ANCHOR_HMAX": 15,
    "ANCHOR_RECESS": 0,
    "FLOOR_CLIPS": "FIXED",
    "BASE_CLIPS": 0,
    "CLOSER": true,
    "CLOSER_TYPE": 1,
    "SURFACE_CLOSER_LENGTH": 21,
    "SURFACE_CLOSER_WIDTH": 5,
    "SURFACE_CLOSER_LENGTH_2": 21,
    "SURFACE_CLOSER_WIDTH_2": 5.25,
    "HS_LENGTH": 21,
    "HS_LENGTH_2": 21,
    "EQUAL_CLOSERS": true,
    "FLUSH_BOLT_CENTER_TOP": 12,
    "FLUSH_BOLT_CENTER_BOTTOM": 12,
    "FLUSH_PULL_CENTER": 50,
    "FLUSH_PULL_BACKSET": 2.75,
    "PUSH_PULL_WIDTH": 5,
    "PUSH_PULL_HEIGHT": 18,
    "PUSH_PLATE_CENTER": 45,
    "PUSH_BAR_CENTER": 45,
    "PULL_PLATE_CENTER": 45,
    "PULL_PLATE_HEIGHT": 16,
    "EQUAL_PUSH_PULLS": 1,
    "KICK_PLATE_WIDTH": 99,
    "KICK_PLATE_GAUGE": 18,
    "DPS_LOCATION": 6,
    "DPS_POSITION": 0,
    "EQUAL_DPS": true,
    "GLASS_SUPPLIER": "OTHERS",
    "GLASS_INSTALLER": "OTHERS",
    "GLASS_STOP_WIDTH": 0.625,
    "MAX_GLAZING_HOLE_SPACE": 8,
    "DOOR_LITE_TRIM_TYPE": "B",
    "DOOR_LITE_TRIM_GAUGE": 18,
    "STEEL_STIFFENER_MATERIAL": 0,
    "STEEL_STIFFENER_GAUGE": 22,
    "STEEL_STIFFENER_INSULATION": 0,
    "STEEL_STIFFENER_WIDTH": 2,
    "MAXIMUM_STIFFENER_CTR": 8,
    "FRAME_WELD_ALLOWANCE_FACE": 0.04,
    "FRAME_WELD_ALLOWANCE_FULLY": 0.12,
    "HEAD_GRAIN": "VERTICAL",
    "MANUFACTURERS_LOCATIONS": "SDI",
    "MAT_TYPE": "SS",
    "BEVEL": 4,
    "ASTRAGAL_WIDTH": 2,
    "ACTIVE_LEAF": 99,
    "SILENCER_HOLE_DIA": 0.281,
    "EQUAL_ELEVATIONS": true,
    "CLOSED_BACK": false,
    "WEEP_HOLES": false
  },
  "createdAt": "2025-12-01T03:02:00.760Z"
}