{
  "formId": "exit-device",
  "itemType": "custom",
  "title": "Exit Device",
  "description": "Configuration parameters for exit device",
  "sections": [
    {
      "id": "exit-device-configuration",
      "title": "Configuration",
      "fields": [
        {
          "id": "exit-device-strike-center",
          "name": "STRIKE_CENTER",
          "label": "Strike Center",
          "required": false,
          "type": "float",
          "placeholder": "0.00"
        }
      ]
    }
  ],
  "submitButton": {
    "text": "Save Configuration",
    "action": "save-config"
  }
}